setup.py
google/__init__.py
google/__init__.pyi
google/iam/__init__.py
google/iam/__init__.pyi
google/iam/admin/__init__.py
google/iam/admin/__init__.pyi
google/iam/admin/v1/__init__.py
google/iam/admin/v1/__init__.pyi
google/iam/admin/v1/iam_pb2.py
google/iam/admin/v1/iam_pb2.pyi
google/iam/admin/v1/iam_pb2_grpc.py
google/iam/admin/v1/iam_pb2_grpc.pyi
google/iam/v1/__init__.py
google/iam/v1/__init__.pyi
google/iam/v1/iam_policy_pb2.py
google/iam/v1/iam_policy_pb2.pyi
google/iam/v1/iam_policy_pb2_grpc.py
google/iam/v1/iam_policy_pb2_grpc.pyi
google/iam/v1/options_pb2.py
google/iam/v1/options_pb2.pyi
google/iam/v1/options_pb2_grpc.py
google/iam/v1/options_pb2_grpc.pyi
google/iam/v1/policy_pb2.py
google/iam/v1/policy_pb2.pyi
google/iam/v1/policy_pb2_grpc.py
google/iam/v1/policy_pb2_grpc.pyi
google_common_protos.egg-info/PKG-INFO
google_common_protos.egg-info/SOURCES.txt
google_common_protos.egg-info/dependency_links.txt
google_common_protos.egg-info/top_level.txt