Metadata-Version: 2.4
Name: google-common-protos
Version: 1.27.1
Summary: Protobufs generated by Alis Build
Dynamic: summary
